{
  "lang": "es", 
  "pipeline": [
    "ner"
  ], 
  "accuracy": {
    "token_acc": 100.0, 
    "ents_p": 52.7918781726, 
    "ents_r": 50.7317073171, 
    "uas": 0.0, 
    "tags_acc": 0.0, 
    "ents_f": 51.7412935323, 
    "las": 0.0
  }, 
  "name": "ent_wiki_sm", 
  "license": "CC BY-SA 3.0", 
  "author": "Explosion AI", 
  "url": "https://explosion.ai", 
  "checksum": "8c8df1253453ccbb1e0f4b5bf4cf15a397591a15612ebadfa649d551200f2ee5", 
  "notes": "Because the model is trained on Wikipedia, it may perform inconsistently on many genres, such as social media text.", 
  "size": "12 MB", 
  "sources": [
    "Wikipedia"
  ], 
  "version": "2.0.0a0", 
  "spacy_version": ">=2.0.0a15", 
  "parent_package": "spacy-nightly", 
  "email": "contact@explosion.ai", 
  "description": "Spanish CNN trained on Nothman et al. (2010) Wikipedia corpus. Assigns named entities. Supports identification of PER, LOC, ORG and MISC entities."
}